nightforo/__init__.py
nightforo/api_scopes.py
nightforo/client.py
nightforo/endpoint.py
nightforo/endpoints.py
nightforo/errors.py
nightforo/groups.py
nightforo/http.py
nightforo/types/file.py
nightforo/types/pagination.py
nightforo/types/vote_type.py
nightforo/types/alert/__init__.py
nightforo/types/alert/alert.py
nightforo/types/alert/params.py
nightforo/types/alert/response.py
nightforo/types/attachment/__init__.py
nightforo/types/attachment/attachment.py
nightforo/types/attachment/params.py
nightforo/types/attachment/response.py
nightforo/types/auth/__init__.py
nightforo/types/auth/params.py
nightforo/types/auth/response.py
nightforo/types/conversation/__init__.py
nightforo/types/conversation/conversation.py
nightforo/types/conversation/params.py
nightforo/types/conversation/response.py
nightforo/types/conversation_message/__init__.py
nightforo/types/conversation_message/conversation_message.py
nightforo/types/conversation_message/params.py
nightforo/types/conversation_message/response.py
nightforo/types/forum/__init__.py
nightforo/types/forum/forum.py
nightforo/types/forum/params.py
nightforo/types/forum/response.py
nightforo/types/me/__init__.py
nightforo/types/me/params.py
nightforo/types/me/response.py
nightforo/types/node/__init__.py
nightforo/types/node/node.py
nightforo/types/node/params.py
nightforo/types/node/response.py
nightforo/types/page/__init__.py
nightforo/types/page/page.py
nightforo/types/page/response.py
nightforo/types/post/__init__.py
nightforo/types/post/params.py
nightforo/types/post/post.py
nightforo/types/post/response.py
nightforo/types/profile_post/__init__.py
nightforo/types/profile_post/params.py
nightforo/types/profile_post/profile_post.py
nightforo/types/profile_post/response.py
nightforo/types/profile_post_comment/__init__.py
nightforo/types/profile_post_comment/params.py
nightforo/types/profile_post_comment/profile_post_comment.py
nightforo/types/profile_post_comment/response.py
nightforo/types/stats/__init__.py
nightforo-1.1.4.dist-info/licenses/LICENSE
nightforo-1.1.4.dist-info/METADATA
nightforo-1.1.4.dist-info/WHEEL
nightforo-1.1.4.dist-info/top_level.txt
nightforo-1.1.4.dist-info/RECORD
