Metadata-Version: 2.4
Name: nightforo
Version: 1.1.4
Summary: API wrapper for Arizona Guard written in Python
Author: nightcore-team
License-Expression: MIT
Project-URL: Repository, https://github.com/nightcore-team/NightForo
Requires-Python: >=3.8
License-File: LICENSE
Requires-Dist: aiohttp>=3.10.11
Requires-Dist: pydantic>=2.10.6
Dynamic: license-file
